routingkit_cch-0.1.3.dist-info/METADATA
routingkit_cch-0.1.3.dist-info/WHEEL
routingkit_cch.libs/libgcc_s-39080030.so.1
routingkit_cch.libs/libstdc++-cedf4250.so.6
routingkit_cch/__init__.py
routingkit_cch/__init__.pyi
routingkit_cch/py.typed
routingkit_cch/routingkit_cch.cpython-312-aarch64-linux-musl.so
routingkit_cch-0.1.3.dist-info/RECORD
