Metadata-Version: 2.4
Name: routingkit_cch
Version: 0.1.3
Classifier: Programming Language :: Rust
Classifier: Programming Language :: Python :: Implementation :: CPython
Classifier: Programming Language :: Python :: Implementation :: PyPy
Summary: Python bindings for the Customizable Contraction Hierarchies (CCH) implementation from RoutingKit.
Author-email: HellOwhatAs <xjq701229@outlook.com>
Requires-Python: >=3.8
Project-URL: Repository, https://github.com/HellOwhatAs/routingkit-cch
